[
  {
    "query": "High-return rentals in Springfield under $1500",
    "id": "1530-E-Melrose-St,-Springfield,-IL-62703",
    "relevance": 2
  },
  {
    "query": "High-return rentals in Springfield under $1500",
    "id": "564-W-Elliott-Ave,-Springfield,-IL-62702",
    "relevance": 2
  },
  {
    "query": "High-return rentals in Springfield under $1500",
    "id": "1422-E-Reservoir-St,-Springfield,-IL-62702",
    "relevance": 0
  },
  {
    "query": "High-return rentals in Springfield under $1500",
    "id": "155-S-Durkin-Dr,-Apt-7,-Springfield,-IL-62704",
    "relevance": 2
  },
  {
    "query": "High-return rentals in Springfield under $1500",
    "id": "1303-S-12th-St,-Springfield,-IL-62703",
    "relevance": 1
  },
  {
    "query": "High-return rentals in Springfield under $1500",
    "id": "403-S-Main-St,-Apt-D,-Chatham,-IL-62629",
    "relevance": 2
  },
  {
    "query": "High-return rentals in Springfield under $1500",
    "id": "2070-Bradley-Ct,-Apt-B,-Springfield,-IL-62703",
    "relevance": 2
  },
  {
    "query": "High-return rentals in Springfield under $1500",
    "id": "425-W-Lawrence-Ave,-Apt-4,-Springfield,-IL-62704",
    "relevance": 2
  },
  {
    "query": "High-return rentals in Springfield under $1500",
    "id": "500-Old-Tipton-School-Rd,-Sherman,-IL-62684",
    "relevance": 0
  },
  {
    "query": "High-return rentals in Springfield under $1500",
    "id": "841-N-7th-St,-Apt-B,-Springfield,-IL-62702",
    "relevance": 2
  },
  {
    "query": "High-return rentals in Springfield under $1500",
    "id": "21-Cahokia-Dr,-Pawnee,-IL-62558",
    "relevance": 2
  },
  {
    "query": "High-return rentals in Springfield under $1500",
    "id": "421-Dalhlia-Dr,-Chatham,-IL-62629",
    "relevance": 0
  },
  {
    "query": "High-return rentals in Springfield under $1500",
    "id": "2904-West-Blvd,-Apt-1,-Belleville,-IL-62221",
    "relevance": 2
  }
]